videoprocessor/__init__.py
videoprocessor/videoprocessor.py
videoprocessor-0.0.4.dist-info/LICENSE
videoprocessor-0.0.4.dist-info/METADATA
videoprocessor-0.0.4.dist-info/WHEEL
videoprocessor-0.0.4.dist-info/top_level.txt
videoprocessor-0.0.4.dist-info/RECORD
