Metadata-Version: 2.1
Name: videoprocessor
Version: 0.0.4
Summary: A package base on ffmpeg and ffmpeg-python to process video.
Author-email: FogSalary <Kairong_Wu@163.com>
Classifier: Programming Language :: Python :: 3
Classifier: License :: OSI Approved :: MIT License
Classifier: Operating System :: OS Independent
Requires-Python: >=3.7
License-File: LICENSE
